fresh/__init__.py
fresh/_version.py
fresh/model.py
fresh/rust/example.cpython-36m-x86_64-linux-gnu.so
fresh-0.0.1.dist-info/METADATA
fresh-0.0.1.dist-info/RECORD
fresh-0.0.1.dist-info/WHEEL
fresh-0.0.1.dist-info/top_level.txt
