Metadata-Version: 2.1
Name: fresh
Version: 0.0.1
Summary: Automated, end-to-end machine learning
Home-page: https://github.com/milesgranger/fresh
Author: Miles Granger
Author-email: miles59923@gmail.com
Maintainer: Miles Granger
Maintainer-email: miles59923@gmail.com
License: BSD
Keywords: automated machine learning
Platform: UNKNOWN
Classifier: Development Status :: 3 - Alpha
Classifier: Intended Audience :: Developers
Classifier: Intended Audience :: Financial and Insurance Industry
Classifier: Intended Audience :: Information Technology
Classifier: Intended Audience :: Science/Research
Classifier: Programming Language :: Python
Classifier: Programming Language :: Python :: 3.5
Classifier: Programming Language :: Python :: 3.6
Classifier: Programming Language :: Python :: 3 :: Only
Classifier: Programming Language :: Rust
Classifier: Operating System :: Microsoft :: Windows
Classifier: Operating System :: POSIX
Classifier: Operating System :: Unix
Classifier: Operating System :: MacOS :: MacOS X
